{
  "image": "annotated_1765280172319-1c4zvz.JPG",
  "image_path": "/home/praho/WebstormProjects/ADER_App/vineyard-app/backend/uploads/annotated_1765280172319-1c4zvz.JPG",
  "timestamp": "2025-12-09T11:50:04.820Z",
  "industry": "general",
  "confidence_threshold": 0.35,
  "detections": [
    {
      "class": "car",
      "class_id": 2,
      "confidence": 0.765,
      "bbox": {
        "x1": 1515.2431640625,
        "y1": 789.8673095703125,
        "x2": 1832.237060546875,
        "y2": 953.58935546875,
        "width": 316.993896484375,
        "height": 163.7220458984375
      },
      "bbox_normalized": {
        "x_center": 0.5579133629798889,
        "y_center": 0.38743481040000916,
        "width": 0.10566463321447372,
        "height": 0.07276535034179688
      }
    },
    {
      "class": "person",
      "class_id": 0,
      "confidence": 0.736,
      "bbox": {
        "x1": 2094.357177734375,
        "y1": 1650.4033203125,
        "x2": 2199.197509765625,
        "y2": 1859.08642578125,
        "width": 104.84033203125,
        "height": 208.68310546875
      },
      "bbox_normalized": {
        "x_center": 0.7155924439430237,
        "y_center": 0.7798866033554077,
        "width": 0.03494677692651749,
        "height": 0.09274804592132568
      }
    },
    {
      "class": "person",
      "class_id": 0,
      "confidence": 0.68,
      "bbox": {
        "x1": 1912.6593017578125,
        "y1": 1125.812255859375,
        "x2": 1970.837646484375,
        "y2": 1266.9595947265625,
        "width": 58.1783447265625,
        "height": 141.1473388671875
      },
      "bbox_normalized": {
        "x_center": 0.6472495198249817,
        "y_center": 0.5317270755767822,
        "width": 0.01939278095960617,
        "height": 0.06273215264081955
      }
    },
    {
      "class": "person",
      "class_id": 0,
      "confidence": 0.676,
      "bbox": {
        "x1": 1343.8836669921875,
        "y1": 1161.007080078125,
        "x2": 1388.5098876953125,
        "y2": 1311.847900390625,
        "width": 44.626220703125,
        "height": 150.8408203125
      },
      "bbox_normalized": {
        "x_center": 0.45539891719818115,
        "y_center": 0.5495233535766602,
        "width": 0.014875407330691814,
        "height": 0.06704036146402359
      }
    },
    {
      "class": "person",
      "class_id": 0,
      "confidence": 0.675,
      "bbox": {
        "x1": 1841.6136474609375,
        "y1": 856.268798828125,
        "x2": 1895.450927734375,
        "y2": 999.8458251953125,
        "width": 53.8372802734375,
        "height": 143.5770263671875
      },
      "bbox_normalized": {
        "x_center": 0.6228440999984741,
        "y_center": 0.41246992349624634,
        "width": 0.01794576086103916,
        "height": 0.0638120099902153
      }
    },
    {
      "class": "person",
      "class_id": 0,
      "confidence": 0.648,
      "bbox": {
        "x1": 1644.7423095703125,
        "y1": 1197.835205078125,
        "x2": 1696.5576171875,
        "y2": 1349.0364990234375,
        "width": 51.8153076171875,
        "height": 151.2012939453125
      },
      "bbox_normalized": {
        "x_center": 0.5568832755088806,
        "y_center": 0.5659714341163635,
        "width": 0.017271768301725388,
        "height": 0.06720057874917984
      }
    },
    {
      "class": "car",
      "class_id": 2,
      "confidence": 0.635,
      "bbox": {
        "x1": 1313.9825439453125,
        "y1": 704.8187255859375,
        "x2": 1569.5513916015625,
        "y2": 816.798828125,
        "width": 255.56884765625,
        "height": 111.9801025390625
      },
      "bbox_normalized": {
        "x_center": 0.48058900237083435,
        "y_center": 0.3381372392177582,
        "width": 0.08518961817026138,
        "height": 0.04976893588900566
      }
    },
    {
      "class": "person",
      "class_id": 0,
      "confidence": 0.635,
      "bbox": {
        "x1": 1109.302490234375,
        "y1": 1291.17041015625,
        "x2": 1180.492919921875,
        "y2": 1455.2901611328125,
        "width": 71.1904296875,
        "height": 164.1197509765625
      },
      "bbox_normalized": {
        "x_center": 0.38163256645202637,
        "y_center": 0.6103245615959167,
        "width": 0.023730143904685974,
        "height": 0.0729421079158783
      }
    },
    {
      "class": "person",
      "class_id": 0,
      "confidence": 0.613,
      "bbox": {
        "x1": 1068.5943603515625,
        "y1": 1492.0057373046875,
        "x2": 1140.32666015625,
        "y2": 1643.5157470703125,
        "width": 71.7322998046875,
        "height": 151.510009765625
      },
      "bbox_normalized": {
        "x_center": 0.36815348267555237,
        "y_center": 0.6967825293540955,
        "width": 0.02391076646745205,
        "height": 0.06733778119087219
      }
    },
    {
      "class": "kite",
      "class_id": 33,
      "confidence": 0.35,
      "bbox": {
        "x1": 806.72119140625,
        "y1": 1791.667236328125,
        "x2": 1210.2803955078125,
        "y2": 2154.001953125,
        "width": 403.5592041015625,
        "height": 362.334716796875
      },
      "bbox_normalized": {
        "x_center": 0.3361669182777405,
        "y_center": 0.8768153786659241,
        "width": 0.13451974093914032,
        "height": 0.1610376536846161
      }
    }
  ],
  "detection_count": 10,
  "manual_corrections": [],
  "status": "auto_annotated"
}